sketchkit/__init__.py
sketchkit/core/__init__.py
sketchkit/core/sketch.py
sketchkit/core/sketch3d.py
sketchkit/datasets/__init__.py
sketchkit/datasets/controlsketch.py
sketchkit/datasets/creative_sketch.py
sketchkit/datasets/differsketching.py
sketchkit/datasets/fscoco.py
sketchkit/datasets/gmu_sketch_cleanup.py
sketchkit/datasets/hzy_sketch.py
sketchkit/datasets/opensketch.py
sketchkit/datasets/photosketching.py
sketchkit/datasets/quickdraw.py
sketchkit/datasets/sketchx_pris.py
sketchkit/datasets/sketchy.py
sketchkit/datasets/tracing_vs_freehand.py
sketchkit/datasets/tu_berlin.py
sketchkit/models/__init__.py
sketchkit/renderer/cairo_renderer.py
sketchkit/utils/__init__.py
sketchkit/utils/dataset.py
sketchkit/utils/file.py
sketchkit/utils/geometry.py
sketchkit/utils/transform.py
sketchkit-0.0.1.dist-info/METADATA
sketchkit-0.0.1.dist-info/WHEEL
sketchkit-0.0.1.dist-info/top_level.txt
sketchkit-0.0.1.dist-info/RECORD
