Metadata-Version: 2.4
Name: sketchkit
Version: 0.0.1
Summary: An universal toolkit for sketching
Requires-Python: >=3.12
Requires-Dist: cairocffi>=1.7.1
Requires-Dist: fastparquet>=2024.11.0
Requires-Dist: gdown>=5.2.0
Requires-Dist: ndjson>=0.3.1
Requires-Dist: pandas>=2.3.2
Requires-Dist: patool>=4.0.1
Requires-Dist: py7zr>=1.0.0
Requires-Dist: pyunpack>=0.3
Requires-Dist: rich>=14.1.0
Requires-Dist: svg-path>=7.0
Requires-Dist: svgpathtools>=1.7.1
Requires-Dist: torch>=2.8.0
Requires-Dist: torchvision>=0.23.0
Requires-Dist: wget>=3.2
